
<stlocds stlocds_id="@stlocds_id_pt_BR_1" stloc_id="@stloc_id_1" language_id="&pt_BR;" name="Sherway Gardens" description="Sherway Gardens" />
<stlocds stlocds_id="@stlocds_id_pt_BR_2" stloc_id="@stloc_id_2" language_id="&pt_BR;" name="Yorkdale Centre" description="Yorkdale Centre" />
<stlocds stlocds_id="@stlocds_id_pt_BR_3" stloc_id="@stloc_id_3" language_id="&pt_BR;" name="Markham Centre" description="Markham Centre" />
<stlocds stlocds_id="@stlocds_id_pt_BR_4" stloc_id="@stloc_id_4" language_id="&pt_BR;" name="Markville Mall" description="Markville Mall" />
<stlocds stlocds_id="@stlocds_id_pt_BR_5" stloc_id="@stloc_id_5" language_id="&pt_BR;" name="Burnaby Center" description="Burnaby Center" />
<stlocds stlocds_id="@stlocds_id_pt_BR_6" stloc_id="@stloc_id_6" language_id="&pt_BR;" name="Eaton Centre" description="Eaton Centre" />
<stlocds stlocds_id="@stlocds_id_pt_BR_7" stloc_id="@stloc_id_7" language_id="&pt_BR;" name="University Avenue" description="University Avenue" />
<stlocds stlocds_id="@stlocds_id_pt_BR_8" stloc_id="@stloc_id_8" language_id="&pt_BR;" name="Parkside Mall" description="Parkside Mall" />
<stlocds stlocds_id="@stlocds_id_pt_BR_9" stloc_id="@stloc_id_9" language_id="&pt_BR;" name="Pacific Mall" description="Pacific Mall" />
<stlocds stlocds_id="@stlocds_id_pt_BR_10" stloc_id="@stloc_id_10" language_id="&pt_BR;" name="Vancouver Mall" description="Vancouver Mall" />
<stlocds stlocds_id="@stlocds_id_pt_BR_11" stloc_id="@stloc_id_11" language_id="&pt_BR;" name="Breakfast Place" description="Breakfast Place" />
<stlocds stlocds_id="@stlocds_id_pt_BR_12" stloc_id="@stloc_id_12" language_id="&pt_BR;" name="Regina Centre" description="Regina Centre" />
<stlocds stlocds_id="@stlocds_id_pt_BR_13" stloc_id="@stloc_id_13" language_id="&pt_BR;" name="Edmonton Place" description="Edmonton Place" />
<stlocds stlocds_id="@stlocds_id_pt_BR_14" stloc_id="@stloc_id_14" language_id="&pt_BR;" name="Victoria Place" description="Victoria Place" />
<stlocds stlocds_id="@stlocds_id_pt_BR_15" stloc_id="@stloc_id_15" language_id="&pt_BR;" name="New Brunswick Place" description="New Brunswick Place" />
<stlocds stlocds_id="@stlocds_id_pt_BR_16" stloc_id="@stloc_id_16" language_id="&pt_BR;" name="Newfoundland Place" description="Newfoundland Place" />
<stlocds stlocds_id="@stlocds_id_pt_BR_17" stloc_id="@stloc_id_17" language_id="&pt_BR;" name="Nova Scotia Place" description="Nova Scotia Place" />
<stlocds stlocds_id="@stlocds_id_pt_BR_18" stloc_id="@stloc_id_18" language_id="&pt_BR;" name="Montreal Place" description="Montreal Place" />
<stlocds stlocds_id="@stlocds_id_pt_BR_19" stloc_id="@stloc_id_19" language_id="&pt_BR;" name="Quebec Place" description="Quebec Place" />
<stlocds stlocds_id="@stlocds_id_pt_BR_20" stloc_id="@stloc_id_20" language_id="&pt_BR;" name="ColwoodBC" description="ColwoodBC" />
<stlocds stlocds_id="@stlocds_id_pt_BR_21" stloc_id="@stloc_id_21" language_id="&pt_BR;" name="NanaimoBC" description="NanaimoBC" />
<stlocds stlocds_id="@stlocds_id_pt_BR_22" stloc_id="@stloc_id_22" language_id="&pt_BR;" name="VicBC2" description="VicBC2" />
<stlocds stlocds_id="@stlocds_id_pt_BR_23" stloc_id="@stloc_id_23" language_id="&pt_BR;" name="Chilliwack" description="Chilliwack" />
<stlocds stlocds_id="@stlocds_id_pt_BR_24" stloc_id="@stloc_id_24" language_id="&pt_BR;" name="MedicineHat" description="MedicineHat" />
<stlocds stlocds_id="@stlocds_id_pt_BR_25" stloc_id="@stloc_id_25" language_id="&pt_BR;" name="Edmonton2" description="Edmonton2" />
<stlocds stlocds_id="@stlocds_id_pt_BR_26" stloc_id="@stloc_id_26" language_id="&pt_BR;" name="Calgary Mall" description="Calgary Mall" />
<stlocds stlocds_id="@stlocds_id_pt_BR_27" stloc_id="@stloc_id_27" language_id="&pt_BR;" name="Winnipeg Mall" description="Winnipeg Mall" />
<stlocds stlocds_id="@stlocds_id_pt_BR_28" stloc_id="@stloc_id_28" language_id="&pt_BR;" name="Waterloo Mall" description="Waterloo Mall" />
<stlocds stlocds_id="@stlocds_id_pt_BR_29" stloc_id="@stloc_id_29" language_id="&pt_BR;" name="Laval Mall" description="Laval Mall" />
<stlocds stlocds_id="@stlocds_id_pt_BR_30" stloc_id="@stloc_id_30" language_id="&pt_BR;" name="Montreal Mall" description="Montreal Mall" />
<stlocds stlocds_id="@stlocds_id_pt_BR_31" stloc_id="@stloc_id_31" language_id="&pt_BR;" name="QC Mall" description="QC Mall" />
<stlocds stlocds_id="@stlocds_id_pt_BR_32" stloc_id="@stloc_id_32" language_id="&pt_BR;" name="Charlottetown Mall" description="Charlottetown Mall" />
<stlocds stlocds_id="@stlocds_id_pt_BR_33" stloc_id="@stloc_id_33" language_id="&pt_BR;" name="Fredericton Mall" description="Fredericton Mall" />
<stlocds stlocds_id="@stlocds_id_pt_BR_34" stloc_id="@stloc_id_34" language_id="&pt_BR;" name="Fredericton Square" description="Fredericton Square" />
<stlocds stlocds_id="@stlocds_id_pt_BR_35" stloc_id="@stloc_id_35" language_id="&pt_BR;" name="Moncton Square" description="Moncton Square" />
<stlocds stlocds_id="@stlocds_id_pt_BR_36" stloc_id="@stloc_id_36" language_id="&pt_BR;" name="NFLD Mall" description="NFLD Mall" />
<stlocds stlocds_id="@stlocds_id_pt_BR_37" stloc_id="@stloc_id_37" language_id="&pt_BR;" name="Calgary Circle Mall" description="Calgary Circle Mall" />
<stlocds stlocds_id="@stlocds_id_pt_BR_38" stloc_id="@stloc_id_38" language_id="&pt_BR;" name="London Alberta Mall" description="London Alberta Mall" />
<stlocds stlocds_id="@stlocds_id_pt_BR_39" stloc_id="@stloc_id_39" language_id="&pt_BR;" name="Warden Plaza" description="Warden Plaza" />
<stlocds stlocds_id="@stlocds_id_pt_BR_40" stloc_id="@stloc_id_40" language_id="&pt_BR;" name="Bathurst Plaza" description="Bathurst Plaza" />
<stlocds stlocds_id="@stlocds_id_pt_BR_41" stloc_id="@stloc_id_41" language_id="&pt_BR;" name="Keele Plaza" description="Keele Plaza" />
<stlocds stlocds_id="@stlocds_id_pt_BR_42" stloc_id="@stloc_id_42" language_id="&pt_BR;" name="Alton Towers Plaza" description="Alton Towers Plaza" />
<stlocds stlocds_id="@stlocds_id_pt_BR_43" stloc_id="@stloc_id_43" language_id="&pt_BR;" name="City Centre Plaza" description="City Centre Plaza" />
<stlocds stlocds_id="@stlocds_id_pt_BR_44" stloc_id="@stloc_id_44" language_id="&pt_BR;" name="Borough Plaza" description="Borough Plaza" />
<stlocds stlocds_id="@stlocds_id_pt_BR_45" stloc_id="@stloc_id_45" language_id="&pt_BR;" name="Bloor Plaza" description="Bloor Plaza" />
<stlocds stlocds_id="@stlocds_id_pt_BR_46" stloc_id="@stloc_id_46" language_id="&pt_BR;" name="Bay Plaza" description="Bay Plaza" />
<stlocds stlocds_id="@stlocds_id_pt_BR_47" stloc_id="@stloc_id_47" language_id="&pt_BR;" name="Islington Plaza" description="Islington Plaza" />
<stlocds stlocds_id="@stlocds_id_pt_BR_48" stloc_id="@stloc_id_48" language_id="&pt_BR;" name="DANFORTH Plaza" description="DANFORTH Plaza" />
<stlocds stlocds_id="@stlocds_id_pt_BR_49" stloc_id="@stloc_id_49" language_id="&pt_BR;" name="Jacksonville Mall" description="Jacksonville Mall" />
<stlocds stlocds_id="@stlocds_id_pt_BR_50" stloc_id="@stloc_id_50" language_id="&pt_BR;" name="Jacksonville Center" description="Jacksonville Center" />
<stlocds stlocds_id="@stlocds_id_pt_BR_51" stloc_id="@stloc_id_51" language_id="&pt_BR;" name="Jacksonville Square" description="Jacksonville Square" />
<stlocds stlocds_id="@stlocds_id_pt_BR_52" stloc_id="@stloc_id_52" language_id="&pt_BR;" name="Jacksonville Outlet" description="Jacksonville Outlet" />
<stlocds stlocds_id="@stlocds_id_pt_BR_53" stloc_id="@stloc_id_53" language_id="&pt_BR;" name="Miami Mall" description="Miami Mall" />
<stlocds stlocds_id="@stlocds_id_pt_BR_54" stloc_id="@stloc_id_54" language_id="&pt_BR;" name="Miami Center" description="Miami Center" />
<stlocds stlocds_id="@stlocds_id_pt_BR_55" stloc_id="@stloc_id_55" language_id="&pt_BR;" name="Miami Square" description="Miami Square" />

<stlocattr stlocattr_id="@stlocattr_id_pt_BR_1_stloc_id_1" stloc_id="@stloc_id_1" language_id="&pt_BR;" name="StoreHours" displayname="Horários de Funcionamento" value="Mon-Fri: 10am - 9pm&lt;br /&gt;Sat: 9am - 7pm&lt;br /&gt;Sun: 11am - 6pm&lt;br /&gt;" displayvalue="Seg-Sex: 10h - 21h&lt;br /&gt;Sáb: 9h - 19h&lt;br /&gt;Dom: 11h - 18h&lt;br /&gt;" displayable="1" sequence="99" />
<stlocattr stlocattr_id="@stlocattr_id_pt_BR_2_stloc_id_1" stloc_id="@stloc_id_1" language_id="&pt_BR;" name="BeautyCenter" displayname="Clínica de Estética" value="true" displayvalue="verdadeiro" displayable="1" sequence="1" />
<stlocattr stlocattr_id="@stlocattr_id_pt_BR_3_stloc_id_1" stloc_id="@stloc_id_1" language_id="&pt_BR;" name="Electronics" displayname="Eletrônicos" value="true" displayvalue="verdadeiro" displayable="1" sequence="2" />
<stlocattr stlocattr_id="@stlocattr_id_pt_BR_4_stloc_id_1" stloc_id="@stloc_id_1" language_id="&pt_BR;" name="Type" displayname="Tipo" value="Regular Store" displayvalue="Loja Regular" displayable="1" sequence="3" />

<stlocattr stlocattr_id="@stlocattr_id_pt_BR_1_stloc_id_2" stloc_id="@stloc_id_2" language_id="&pt_BR;" name="StoreHours" displayname="Horários de Funcionamento" value="Mon-Fri: 10am - 9pm&lt;br /&gt;Sat: 9am - 7pm&lt;br /&gt;Sun: 11am - 6pm&lt;br /&gt;" displayvalue="Seg-Sex: 10h - 21h&lt;br /&gt;Sáb: 9h - 19h&lt;br /&gt;Dom: 11h - 18h&lt;br /&gt;" displayable="1" sequence="99" />
<stlocattr stlocattr_id="@stlocattr_id_pt_BR_2_stloc_id_2" stloc_id="@stloc_id_2" language_id="&pt_BR;" name="CappuccinoBar" displayname="Bar Cappuccino" value="true" displayvalue="verdadeiro" displayable="1" sequence="1" />
<stlocattr stlocattr_id="@stlocattr_id_pt_BR_3_stloc_id_2" stloc_id="@stloc_id_2" language_id="&pt_BR;" name="DesignerStudio" displayname="Designer studio" value="true" displayvalue="verdadeiro" displayable="1" sequence="2" />
<stlocattr stlocattr_id="@stlocattr_id_pt_BR_4_stloc_id_2" stloc_id="@stloc_id_2" language_id="&pt_BR;" name="Type" displayname="Tipo" value="Express Store" displayvalue="Loja Expressa" displayable="1" sequence="3" />

<stlocattr stlocattr_id="@stlocattr_id_pt_BR_1_stloc_id_3" stloc_id="@stloc_id_3" language_id="&pt_BR;" name="StoreHours" displayname="Horários de Funcionamento" value="Mon-Fri: 10am - 9pm&lt;br /&gt;Sat: 9am - 7pm&lt;br /&gt;Sun: 11am - 6pm&lt;br /&gt;" displayvalue="Seg-Sex: 10h - 21h&lt;br /&gt;Sáb: 9h - 19h&lt;br /&gt;Dom: 11h - 18h&lt;br /&gt;" displayable="1" sequence="99" />
<stlocattr stlocattr_id="@stlocattr_id_pt_BR_2_stloc_id_3" stloc_id="@stloc_id_3" language_id="&pt_BR;" name="BeautyCenter" displayname="Clínica de Estética" value="true" displayvalue="verdadeiro" displayable="1" sequence="1" />
<stlocattr stlocattr_id="@stlocattr_id_pt_BR_3_stloc_id_3" stloc_id="@stloc_id_3" language_id="&pt_BR;" name="CappuccinoBar" displayname="Bar Cappuccino" value="true" displayvalue="verdadeiro" displayable="1" sequence="2" />
<stlocattr stlocattr_id="@stlocattr_id_pt_BR_4_stloc_id_3" stloc_id="@stloc_id_3" language_id="&pt_BR;" name="Type" displayname="Tipo" value="Regular Store" displayvalue="Loja Regular" displayable="1" sequence="3" />

<stlocattr stlocattr_id="@stlocattr_id_pt_BR_1_stloc_id_4" stloc_id="@stloc_id_4" language_id="&pt_BR;" name="StoreHours" displayname="Horários de Funcionamento" value="Mon-Fri: 10am - 9pm&lt;br /&gt;Sat: 9am - 7pm&lt;br /&gt;Sun: 11am - 6pm&lt;br /&gt;" displayvalue="Seg-Sex: 10h - 21h&lt;br /&gt;Sáb: 9h - 19h&lt;br /&gt;Dom: 11h - 18h&lt;br /&gt;" displayable="1" sequence="99" />
<stlocattr stlocattr_id="@stlocattr_id_pt_BR_2_stloc_id_4" stloc_id="@stloc_id_4" language_id="&pt_BR;" name="DesignerStudio" displayname="Designer studio" value="true" displayvalue="verdadeiro" displayable="1" sequence="1" />
<stlocattr stlocattr_id="@stlocattr_id_pt_BR_3_stloc_id_4" stloc_id="@stloc_id_4" language_id="&pt_BR;" name="Type" displayname="Tipo" value="Express Store" displayvalue="Loja Expressa" displayable="1" sequence="2" />

<stlocattr stlocattr_id="@stlocattr_id_pt_BR_1_stloc_id_5" stloc_id="@stloc_id_5" language_id="&pt_BR;" name="StoreHours" displayname="Horários de Funcionamento" value="Mon-Fri: 10am - 9pm&lt;br /&gt;Sat: 9am - 7pm&lt;br /&gt;Sun: 11am - 6pm&lt;br /&gt;" displayvalue="Seg-Sex: 10h - 21h&lt;br /&gt;Sáb: 9h - 19h&lt;br /&gt;Dom: 11h - 18h&lt;br /&gt;" displayable="1" sequence="99" />
<stlocattr stlocattr_id="@stlocattr_id_pt_BR_2_stloc_id_5" stloc_id="@stloc_id_5" language_id="&pt_BR;" name="DesignerStudio" displayname="Designer studio" value="true" displayvalue="verdadeiro" displayable="1" sequence="1" />
<stlocattr stlocattr_id="@stlocattr_id_pt_BR_3_stloc_id_5" stloc_id="@stloc_id_5" language_id="&pt_BR;" name="Type" displayname="Tipo" value="Outlet Store" displayvalue="Supermercado" displayable="1" sequence="2" />

<stlocattr stlocattr_id="@stlocattr_id_pt_BR_1_stloc_id_6" stloc_id="@stloc_id_6" language_id="&pt_BR;" name="StoreHours" displayname="Horários de Funcionamento" value="Mon-Fri: 10am - 9pm&lt;br /&gt;Sat: 9am - 7pm&lt;br /&gt;Sun: 11am - 6pm&lt;br /&gt;" displayvalue="Seg-Sex: 10h - 21h&lt;br /&gt;Sáb: 9h - 19h&lt;br /&gt;Dom: 11h - 18h&lt;br /&gt;" displayable="1" sequence="99" />
<stlocattr stlocattr_id="@stlocattr_id_pt_BR_2_stloc_id_6" stloc_id="@stloc_id_6" language_id="&pt_BR;" name="DesignerStudio" displayname="Designer studio" value="true" displayvalue="verdadeiro" displayable="1" sequence="1" />
<stlocattr stlocattr_id="@stlocattr_id_pt_BR_3_stloc_id_6" stloc_id="@stloc_id_6" language_id="&pt_BR;" name="Electronics" displayname="Eletrônicos" value="true" displayvalue="verdadeiro" displayable="1" sequence="2" />
<stlocattr stlocattr_id="@stlocattr_id_pt_BR_4_stloc_id_6" stloc_id="@stloc_id_6" language_id="&pt_BR;" name="Type" displayname="Tipo" value="Regular Store" displayvalue="Loja Regular" displayable="1" sequence="3" />

<stlocattr stlocattr_id="@stlocattr_id_pt_BR_1_stloc_id_7" stloc_id="@stloc_id_7" language_id="&pt_BR;" name="StoreHours" displayname="Horários de Funcionamento" value="Mon-Fri: 10am - 9pm&lt;br /&gt;Sat: 9am - 7pm&lt;br /&gt;Sun: 11am - 6pm&lt;br /&gt;" displayvalue="Seg-Sex: 10h - 21h&lt;br /&gt;Sáb: 9h - 19h&lt;br /&gt;Dom: 11h - 18h&lt;br /&gt;" displayable="1" sequence="99" />
<stlocattr stlocattr_id="@stlocattr_id_pt_BR_2_stloc_id_7" stloc_id="@stloc_id_7" language_id="&pt_BR;" name="DesignerStudio" displayname="Designer studio" value="true" displayvalue="verdadeiro" displayable="1" sequence="1" />
<stlocattr stlocattr_id="@stlocattr_id_pt_BR_3_stloc_id_7" stloc_id="@stloc_id_7" language_id="&pt_BR;" name="SushiRestaurant" displayname="Restaurante de Sushi" value="true" displayvalue="verdadeiro" displayable="1" sequence="2" />
<stlocattr stlocattr_id="@stlocattr_id_pt_BR_4_stloc_id_7" stloc_id="@stloc_id_7" language_id="&pt_BR;" name="Type" displayname="Tipo" value="Express Store" displayvalue="Loja Expressa" displayable="1" sequence="3" />

<stlocattr stlocattr_id="@stlocattr_id_pt_BR_1_stloc_id_8" stloc_id="@stloc_id_8" language_id="&pt_BR;" name="StoreHours" displayname="Horários de Funcionamento" value="Mon-Fri: 10am - 9pm&lt;br /&gt;Sat: 9am - 7pm&lt;br /&gt;Sun: 11am - 6pm&lt;br /&gt;" displayvalue="Seg-Sex: 10h - 21h&lt;br /&gt;Sáb: 9h - 19h&lt;br /&gt;Dom: 11h - 18h&lt;br /&gt;" displayable="1" sequence="99" />
<stlocattr stlocattr_id="@stlocattr_id_pt_BR_2_stloc_id_8" stloc_id="@stloc_id_8" language_id="&pt_BR;" name="DesignerStudio" displayname="Designer studio" value="true" displayvalue="verdadeiro" displayable="1" sequence="1" />
<stlocattr stlocattr_id="@stlocattr_id_pt_BR_3_stloc_id_8" stloc_id="@stloc_id_8" language_id="&pt_BR;" name="Type" displayname="Tipo" value="Outlet Store" displayvalue="Supermercado" displayable="1" sequence="2" />

<stlocattr stlocattr_id="@stlocattr_id_pt_BR_1_stloc_id_9" stloc_id="@stloc_id_9" language_id="&pt_BR;" name="StoreHours" displayname="Horários de Funcionamento" value="Mon-Fri: 10am - 9pm&lt;br /&gt;Sat: 9am - 7pm&lt;br /&gt;Sun: 11am - 6pm&lt;br /&gt;" displayvalue="Seg-Sex: 10h - 21h&lt;br /&gt;Sáb: 9h - 19h&lt;br /&gt;Dom: 11h - 18h&lt;br /&gt;" displayable="1" sequence="99" />
<stlocattr stlocattr_id="@stlocattr_id_pt_BR_2_stloc_id_9" stloc_id="@stloc_id_9" language_id="&pt_BR;" name="DesignerStudio" displayname="Designer studio" value="true" displayvalue="verdadeiro" displayable="1" sequence="1" />
<stlocattr stlocattr_id="@stlocattr_id_pt_BR_3_stloc_id_9" stloc_id="@stloc_id_9" language_id="&pt_BR;" name="Type" displayname="Tipo" value="Regular Store" displayvalue="Loja Regular" displayable="1" sequence="2" />

<stlocattr stlocattr_id="@stlocattr_id_pt_BR_1_stloc_id_10" stloc_id="@stloc_id_10" language_id="&pt_BR;" name="StoreHours" displayname="Horários de Funcionamento" value="Mon-Fri: 10am - 9pm&lt;br /&gt;Sat: 9am - 7pm&lt;br /&gt;Sun: 11am - 6pm&lt;br /&gt;" displayvalue="Seg-Sex: 10h - 21h&lt;br /&gt;Sáb: 9h - 19h&lt;br /&gt;Dom: 11h - 18h&lt;br /&gt;" displayable="1" sequence="99" />
<stlocattr stlocattr_id="@stlocattr_id_pt_BR_2_stloc_id_10" stloc_id="@stloc_id_10" language_id="&pt_BR;" name="SushiRestaurant" displayname="Restaurante de Sushi" value="true" displayvalue="verdadeiro" displayable="1" sequence="1" />
<stlocattr stlocattr_id="@stlocattr_id_pt_BR_3_stloc_id_10" stloc_id="@stloc_id_10" language_id="&pt_BR;" name="Type" displayname="Tipo" value="Express Store" displayvalue="Loja Expressa" displayable="1" sequence="2" />

<stlocattr stlocattr_id="@stlocattr_id_pt_BR_1_stloc_id_11" stloc_id="@stloc_id_11" language_id="&pt_BR;" name="StoreHours" displayname="Horários de Funcionamento" value="Mon-Fri: 10am - 9pm&lt;br /&gt;Sat: 9am - 7pm&lt;br /&gt;Sun: 11am - 6pm&lt;br /&gt;" displayvalue="Seg-Sex: 10h - 21h&lt;br /&gt;Sáb: 9h - 19h&lt;br /&gt;Dom: 11h - 18h&lt;br /&gt;" displayable="1" sequence="99" />
<stlocattr stlocattr_id="@stlocattr_id_pt_BR_2_stloc_id_11" stloc_id="@stloc_id_11" language_id="&pt_BR;" name="Electronics" displayname="Eletrônicos" value="true" displayvalue="verdadeiro" displayable="1" sequence="1" />
<stlocattr stlocattr_id="@stlocattr_id_pt_BR_3_stloc_id_11" stloc_id="@stloc_id_11" language_id="&pt_BR;" name="Type" displayname="Tipo" value="Outlet Store" displayvalue="Supermercado" displayable="1" sequence="2" />

<stlocattr stlocattr_id="@stlocattr_id_pt_BR_1_stloc_id_12" stloc_id="@stloc_id_12" language_id="&pt_BR;" name="StoreHours" displayname="Horários de Funcionamento" value="Mon-Fri: 10am - 9pm&lt;br /&gt;Sat: 9am - 7pm&lt;br /&gt;Sun: 11am - 6pm&lt;br /&gt;" displayvalue="Seg-Sex: 10h - 21h&lt;br /&gt;Sáb: 9h - 19h&lt;br /&gt;Dom: 11h - 18h&lt;br /&gt;" displayable="1" sequence="99" />
<stlocattr stlocattr_id="@stlocattr_id_pt_BR_2_stloc_id_12" stloc_id="@stloc_id_12" language_id="&pt_BR;" name="DesignerStudio" displayname="Designer studio" value="true" displayvalue="verdadeiro" displayable="1" sequence="1" />
<stlocattr stlocattr_id="@stlocattr_id_pt_BR_3_stloc_id_12" stloc_id="@stloc_id_12" language_id="&pt_BR;" name="CappuccinoBar" displayname="Bar Cappuccino" value="true" displayvalue="verdadeiro" displayable="1" sequence="2" />
<stlocattr stlocattr_id="@stlocattr_id_pt_BR_4_stloc_id_12" stloc_id="@stloc_id_12" language_id="&pt_BR;" name="Type" displayname="Tipo" value="Regular Store" displayvalue="Loja Regular" displayable="1" sequence="3" />

<stlocattr stlocattr_id="@stlocattr_id_pt_BR_1_stloc_id_13" stloc_id="@stloc_id_13" language_id="&pt_BR;" name="StoreHours" displayname="Horários de Funcionamento" value="Mon-Fri: 10am - 9pm&lt;br /&gt;Sat: 9am - 7pm&lt;br /&gt;Sun: 11am - 6pm&lt;br /&gt;" displayvalue="Seg-Sex: 10h - 21h&lt;br /&gt;Sáb: 9h - 19h&lt;br /&gt;Dom: 11h - 18h&lt;br /&gt;" displayable="1" sequence="99" />
<stlocattr stlocattr_id="@stlocattr_id_pt_BR_2_stloc_id_13" stloc_id="@stloc_id_13" language_id="&pt_BR;" name="Electronics" displayname="Eletrônicos" value="true" displayvalue="verdadeiro" displayable="1" sequence="1" />
<stlocattr stlocattr_id="@stlocattr_id_pt_BR_3_stloc_id_13" stloc_id="@stloc_id_13" language_id="&pt_BR;" name="Type" displayname="Tipo" value="Express Store" displayvalue="Loja Expressa" displayable="1" sequence="2" />

<stlocattr stlocattr_id="@stlocattr_id_pt_BR_1_stloc_id_14" stloc_id="@stloc_id_14" language_id="&pt_BR;" name="StoreHours" displayname="Horários de Funcionamento" value="Mon-Fri: 10am - 9pm&lt;br /&gt;Sat: 9am - 7pm&lt;br /&gt;Sun: 11am - 6pm&lt;br /&gt;" displayvalue="Seg-Sex: 10h - 21h&lt;br /&gt;Sáb: 9h - 19h&lt;br /&gt;Dom: 11h - 18h&lt;br /&gt;" displayable="1" sequence="99" />
<stlocattr stlocattr_id="@stlocattr_id_pt_BR_2_stloc_id_14" stloc_id="@stloc_id_14" language_id="&pt_BR;" name="SushiRestaurant" displayname="Restaurante de Sushi" value="true" displayvalue="verdadeiro" displayable="1" sequence="2" />
<stlocattr stlocattr_id="@stlocattr_id_pt_BR_3_stloc_id_14" stloc_id="@stloc_id_14" language_id="&pt_BR;" name="CappuccinoBar" displayname="Bar Cappuccino" value="true" displayvalue="verdadeiro" displayable="1" sequence="1" />
<stlocattr stlocattr_id="@stlocattr_id_pt_BR_4_stloc_id_14" stloc_id="@stloc_id_14" language_id="&pt_BR;" name="Electronics" displayname="Eletrônicos" value="true" displayvalue="verdadeiro" displayable="1" sequence="2" />
<stlocattr stlocattr_id="@stlocattr_id_pt_BR_5_stloc_id_14" stloc_id="@stloc_id_14" language_id="&pt_BR;" name="Type" displayname="Tipo" value="Outlet Store" displayvalue="Supermercado" displayable="1" sequence="3" />

<stlocattr stlocattr_id="@stlocattr_id_pt_BR_1_stloc_id_15" stloc_id="@stloc_id_15" language_id="&pt_BR;" name="StoreHours" displayname="Horários de Funcionamento" value="Mon-Fri: 10am - 9pm&lt;br /&gt;Sat: 9am - 7pm&lt;br /&gt;Sun: 11am - 6pm&lt;br /&gt;" displayvalue="Seg-Sex: 10h - 21h&lt;br /&gt;Sáb: 9h - 19h&lt;br /&gt;Dom: 11h - 18h&lt;br /&gt;" displayable="1" sequence="99" />
<stlocattr stlocattr_id="@stlocattr_id_pt_BR_2_stloc_id_15" stloc_id="@stloc_id_15" language_id="&pt_BR;" name="DesignerStudio" displayname="Designer studio" value="true" displayvalue="verdadeiro" displayable="1" sequence="1" />
<stlocattr stlocattr_id="@stlocattr_id_pt_BR_3_stloc_id_15" stloc_id="@stloc_id_15" language_id="&pt_BR;" name="Type" displayname="Tipo" value="Regular Store" displayvalue="Loja Regular" displayable="1" sequence="2" />

<stlocattr stlocattr_id="@stlocattr_id_pt_BR_1_stloc_id_16" stloc_id="@stloc_id_16" language_id="&pt_BR;" name="StoreHours" displayname="Horários de Funcionamento" value="Mon-Fri: 10am - 9pm&lt;br /&gt;Sat: 9am - 7pm&lt;br /&gt;Sun: 11am - 6pm&lt;br /&gt;" displayvalue="Seg-Sex: 10h - 21h&lt;br /&gt;Sáb: 9h - 19h&lt;br /&gt;Dom: 11h - 18h&lt;br /&gt;" displayable="1" sequence="99" />
<stlocattr stlocattr_id="@stlocattr_id_pt_BR_2_stloc_id_16" stloc_id="@stloc_id_16" language_id="&pt_BR;" name="DesignerStudio" displayname="Designer studio" value="true" displayvalue="verdadeiro" displayable="1" sequence="1" />
<stlocattr stlocattr_id="@stlocattr_id_pt_BR_3_stloc_id_16" stloc_id="@stloc_id_16" language_id="&pt_BR;" name="Type" displayname="Tipo" value="Express Store" displayvalue="Loja Expressa" displayable="1" sequence="2" />

<stlocattr stlocattr_id="@stlocattr_id_pt_BR_1_stloc_id_17" stloc_id="@stloc_id_17" language_id="&pt_BR;" name="StoreHours" displayname="Horários de Funcionamento" value="Mon-Fri: 10am - 9pm&lt;br /&gt;Sat: 9am - 7pm&lt;br /&gt;Sun: 11am - 6pm&lt;br /&gt;" displayvalue="Seg-Sex: 10h - 21h&lt;br /&gt;Sáb: 9h - 19h&lt;br /&gt;Dom: 11h - 18h&lt;br /&gt;" displayable="1" sequence="99" />
<stlocattr stlocattr_id="@stlocattr_id_pt_BR_2_stloc_id_17" stloc_id="@stloc_id_17" language_id="&pt_BR;" name="DesignerStudio" displayname="Designer studio" value="true" displayvalue="verdadeiro" displayable="1" sequence="1" />
<stlocattr stlocattr_id="@stlocattr_id_pt_BR_3_stloc_id_17" stloc_id="@stloc_id_17" language_id="&pt_BR;" name="BeautyCenter" displayname="Clínica de Estética" value="true" displayvalue="verdadeiro" displayable="1" sequence="2" />
<stlocattr stlocattr_id="@stlocattr_id_pt_BR_4_stloc_id_17" stloc_id="@stloc_id_17" language_id="&pt_BR;" name="Type" displayname="Tipo" value="Outlet Store" displayvalue="Supermercado" displayable="1" sequence="3" />

<stlocattr stlocattr_id="@stlocattr_id_pt_BR_1_stloc_id_18" stloc_id="@stloc_id_18" language_id="&pt_BR;" name="StoreHours" displayname="Horários de Funcionamento" value="Mon-Fri: 10am - 9pm&lt;br /&gt;Sat: 9am - 7pm&lt;br /&gt;Sun: 11am - 6pm&lt;br /&gt;" displayvalue="Seg-Sex: 10h - 21h&lt;br /&gt;Sáb: 9h - 19h&lt;br /&gt;Dom: 11h - 18h&lt;br /&gt;" displayable="1" sequence="99" />
<stlocattr stlocattr_id="@stlocattr_id_pt_BR_2_stloc_id_18" stloc_id="@stloc_id_18" language_id="&pt_BR;" name="DesignerStudio" displayname="Designer studio" value="true" displayvalue="verdadeiro" displayable="1" sequence="1" />
<stlocattr stlocattr_id="@stlocattr_id_pt_BR_3_stloc_id_18" stloc_id="@stloc_id_18" language_id="&pt_BR;" name="SushiRestaurant" displayname="Restaurante de Sushi" value="true" displayvalue="verdadeiro" displayable="1" sequence="2" />
<stlocattr stlocattr_id="@stlocattr_id_pt_BR_4_stloc_id_18" stloc_id="@stloc_id_18" language_id="&pt_BR;" name="Type" displayname="Tipo" value="Regular Store" displayvalue="Loja Regular" displayable="1" sequence="3" />

<stlocattr stlocattr_id="@stlocattr_id_pt_BR_1_stloc_id_19" stloc_id="@stloc_id_19" language_id="&pt_BR;" name="StoreHours" displayname="Horários de Funcionamento" value="Mon-Fri: 10am - 9pm&lt;br /&gt;Sat: 9am - 7pm&lt;br /&gt;Sun: 11am - 6pm&lt;br /&gt;" displayvalue="Seg-Sex: 10h - 21h&lt;br /&gt;Sáb: 9h - 19h&lt;br /&gt;Dom: 11h - 18h&lt;br /&gt;" displayable="1" sequence="99" />
<stlocattr stlocattr_id="@stlocattr_id_pt_BR_2_stloc_id_19" stloc_id="@stloc_id_19" language_id="&pt_BR;" name="DesignerStudio" displayname="Designer studio" value="true" displayvalue="verdadeiro" displayable="1" sequence="1" />
<stlocattr stlocattr_id="@stlocattr_id_pt_BR_3_stloc_id_19" stloc_id="@stloc_id_19" language_id="&pt_BR;" name="Type" displayname="Tipo" value="Express Store" displayvalue="Loja Expressa" displayable="1" sequence="2" />

<stlocattr stlocattr_id="@stlocattr_id_pt_BR_1_stloc_id_20" stloc_id="@stloc_id_20" language_id="&pt_BR;" name="StoreHours" displayname="Horários de Funcionamento" value="Mon-Fri: 10am - 9pm&lt;br /&gt;Sat: 9am - 7pm&lt;br /&gt;Sun: 11am - 6pm&lt;br /&gt;" displayvalue="Seg-Sex: 10h - 21h&lt;br /&gt;Sáb: 9h - 19h&lt;br /&gt;Dom: 11h - 18h&lt;br /&gt;" displayable="1" sequence="99" />
<stlocattr stlocattr_id="@stlocattr_id_pt_BR_2_stloc_id_20" stloc_id="@stloc_id_20" language_id="&pt_BR;" name="DesignerStudio" displayname="Designer studio" value="true" displayvalue="verdadeiro" displayable="1" sequence="1" />
<stlocattr stlocattr_id="@stlocattr_id_pt_BR_3_stloc_id_20" stloc_id="@stloc_id_20" language_id="&pt_BR;" name="CappuccinoBar" displayname="Bar Cappuccino" value="true" displayvalue="verdadeiro" displayable="1" sequence="2" />
<stlocattr stlocattr_id="@stlocattr_id_pt_BR_4_stloc_id_20" stloc_id="@stloc_id_20" language_id="&pt_BR;" name="BeautyCenter" displayname="Clínica de Estética" value="true" displayvalue="verdadeiro" displayable="1" sequence="3" />
<stlocattr stlocattr_id="@stlocattr_id_pt_BR_5_stloc_id_20" stloc_id="@stloc_id_20" language_id="&pt_BR;" name="Electronics" displayname="Eletrônicos" value="true" displayvalue="verdadeiro" displayable="1" sequence="4" />
<stlocattr stlocattr_id="@stlocattr_id_pt_BR_6_stloc_id_20" stloc_id="@stloc_id_20" language_id="&pt_BR;" name="SushiRestaurant" displayname="Restaurante de Sushi" value="true" displayvalue="verdadeiro" displayable="1" sequence="5" />
<stlocattr stlocattr_id="@stlocattr_id_pt_BR_7_stloc_id_20" stloc_id="@stloc_id_20" language_id="&pt_BR;" name="Type" displayname="Tipo" value="Outlet Store" displayvalue="Supermercado" displayable="1" sequence="6" />

<stlocattr stlocattr_id="@stlocattr_id_pt_BR_1_stloc_id_21" stloc_id="@stloc_id_21" language_id="&pt_BR;" name="StoreHours" displayname="Horários de Funcionamento" value="Mon-Fri: 10am - 9pm&lt;br /&gt;Sat: 9am - 7pm&lt;br /&gt;Sun: 11am - 6pm&lt;br /&gt;" displayvalue="Seg-Sex: 10h - 21h&lt;br /&gt;Sáb: 9h - 19h&lt;br /&gt;Dom: 11h - 18h&lt;br /&gt;" displayable="1" sequence="99" />
<stlocattr stlocattr_id="@stlocattr_id_pt_BR_2_stloc_id_21" stloc_id="@stloc_id_21" language_id="&pt_BR;" name="BeautyCenter" displayname="Clínica de Estética" value="true" displayvalue="verdadeiro" displayable="1" sequence="1" />
<stlocattr stlocattr_id="@stlocattr_id_pt_BR_3_stloc_id_21" stloc_id="@stloc_id_21" language_id="&pt_BR;" name="Electronics" displayname="Eletrônicos" value="true" displayvalue="verdadeiro" displayable="1" sequence="2" />
<stlocattr stlocattr_id="@stlocattr_id_pt_BR_4_stloc_id_21" stloc_id="@stloc_id_21" language_id="&pt_BR;" name="SushiRestaurant" displayname="Restaurante de Sushi" value="true" displayvalue="verdadeiro" displayable="1" sequence="3" />
<stlocattr stlocattr_id="@stlocattr_id_pt_BR_5_stloc_id_21" stloc_id="@stloc_id_21" language_id="&pt_BR;" name="Type" displayname="Tipo" value="Regular Store" displayvalue="Loja Regular" displayable="1" sequence="4" />

<stlocattr stlocattr_id="@stlocattr_id_pt_BR_1_stloc_id_22" stloc_id="@stloc_id_22" language_id="&pt_BR;" name="StoreHours" displayname="Horários de Funcionamento" value="Mon-Fri: 10am - 9pm&lt;br /&gt;Sat: 9am - 7pm&lt;br /&gt;Sun: 11am - 6pm&lt;br /&gt;" displayvalue="Seg-Sex: 10h - 21h&lt;br /&gt;Sáb: 9h - 19h&lt;br /&gt;Dom: 11h - 18h&lt;br /&gt;" displayable="1" sequence="99" />
<stlocattr stlocattr_id="@stlocattr_id_pt_BR_2_stloc_id_22" stloc_id="@stloc_id_22" language_id="&pt_BR;" name="BeautyCenter" displayname="Clínica de Estética" value="true" displayvalue="verdadeiro" displayable="1" sequence="1" />
<stlocattr stlocattr_id="@stlocattr_id_pt_BR_3_stloc_id_22" stloc_id="@stloc_id_22" language_id="&pt_BR;" name="Electronics" displayname="Eletrônicos" value="true" displayvalue="verdadeiro" displayable="1" sequence="2" />
<stlocattr stlocattr_id="@stlocattr_id_pt_BR_4_stloc_id_22" stloc_id="@stloc_id_22" language_id="&pt_BR;" name="SushiRestaurant" displayname="Restaurante de Sushi" value="true" displayvalue="verdadeiro" displayable="1" sequence="3" />
<stlocattr stlocattr_id="@stlocattr_id_pt_BR_5_stloc_id_22" stloc_id="@stloc_id_22" language_id="&pt_BR;" name="Type" displayname="Tipo" value="Outlet Store" displayvalue="Supermercado" displayable="1" sequence="4" />

<stlocattr stlocattr_id="@stlocattr_id_pt_BR_1_stloc_id_23" stloc_id="@stloc_id_23" language_id="&pt_BR;" name="StoreHours" displayname="Horários de Funcionamento" value="Mon-Fri: 10am - 9pm&lt;br /&gt;Sat: 9am - 7pm&lt;br /&gt;Sun: 11am - 6pm&lt;br /&gt;" displayvalue="Seg-Sex: 10h - 21h&lt;br /&gt;Sáb: 9h - 19h&lt;br /&gt;Dom: 11h - 18h&lt;br /&gt;" displayable="1" sequence="99" />
<stlocattr stlocattr_id="@stlocattr_id_pt_BR_2_stloc_id_23" stloc_id="@stloc_id_23" language_id="&pt_BR;" name="DesignerStudio" displayname="Designer studio" value="true" displayvalue="verdadeiro" displayable="1" sequence="1" />
<stlocattr stlocattr_id="@stlocattr_id_pt_BR_3_stloc_id_23" stloc_id="@stloc_id_23" language_id="&pt_BR;" name="CappuccinoBar" displayname="Bar Cappuccino" value="true" displayvalue="verdadeiro" displayable="1" sequence="2" />
<stlocattr stlocattr_id="@stlocattr_id_pt_BR_4_stloc_id_23" stloc_id="@stloc_id_23" language_id="&pt_BR;" name="BeautyCenter" displayname="Clínica de Estética" value="true" displayvalue="verdadeiro" displayable="1" sequence="3" />
<stlocattr stlocattr_id="@stlocattr_id_pt_BR_5_stloc_id_23" stloc_id="@stloc_id_23" language_id="&pt_BR;" name="Electronics" displayname="Eletrônicos" value="true" displayvalue="verdadeiro" displayable="1" sequence="4" />
<stlocattr stlocattr_id="@stlocattr_id_pt_BR_6_stloc_id_23" stloc_id="@stloc_id_23" language_id="&pt_BR;" name="SushiRestaurant" displayname="Restaurante de Sushi" value="true" displayvalue="verdadeiro" displayable="1" sequence="5" />
<stlocattr stlocattr_id="@stlocattr_id_pt_BR_7_stloc_id_23" stloc_id="@stloc_id_23" language_id="&pt_BR;" name="Type" displayname="Tipo" value="Regular Store" displayvalue="Loja Regular" displayable="1" sequence="6" />

<stlocattr stlocattr_id="@stlocattr_id_pt_BR_1_stloc_id_24" stloc_id="@stloc_id_24" language_id="&pt_BR;" name="StoreHours" displayname="Horários de Funcionamento" value="Mon-Fri: 10am - 9pm&lt;br /&gt;Sat: 9am - 7pm&lt;br /&gt;Sun: 11am - 6pm&lt;br /&gt;" displayvalue="Seg-Sex: 10h - 21h&lt;br /&gt;Sáb: 9h - 19h&lt;br /&gt;Dom: 11h - 18h&lt;br /&gt;" displayable="1" sequence="99" />
<stlocattr stlocattr_id="@stlocattr_id_pt_BR_2_stloc_id_24" stloc_id="@stloc_id_24" language_id="&pt_BR;" name="BeautyCenter" displayname="Clínica de Estética" value="true" displayvalue="verdadeiro" displayable="1" sequence="1" />
<stlocattr stlocattr_id="@stlocattr_id_pt_BR_3_stloc_id_24" stloc_id="@stloc_id_24" language_id="&pt_BR;" name="CappuccinoBar" displayname="Bar Cappuccino" value="true" displayvalue="verdadeiro" displayable="1" sequence="2" />
<stlocattr stlocattr_id="@stlocattr_id_pt_BR_4_stloc_id_24" stloc_id="@stloc_id_24" language_id="&pt_BR;" name="SushiRestaurant" displayname="Restaurante de Sushi" value="true" displayvalue="verdadeiro" displayable="1" sequence="3" />
<stlocattr stlocattr_id="@stlocattr_id_pt_BR_5_stloc_id_24" stloc_id="@stloc_id_24" language_id="&pt_BR;" name="Type" displayname="Tipo" value="Express Store" displayvalue="Loja Expressa" displayable="1" sequence="4" />

<stlocattr stlocattr_id="@stlocattr_id_pt_BR_1_stloc_id_25" stloc_id="@stloc_id_25" language_id="&pt_BR;" name="StoreHours" displayname="Horários de Funcionamento" value="Mon-Fri: 10am - 9pm&lt;br /&gt;Sat: 9am - 7pm&lt;br /&gt;Sun: 11am - 6pm&lt;br /&gt;" displayvalue="Seg-Sex: 10h - 21h&lt;br /&gt;Sáb: 9h - 19h&lt;br /&gt;Dom: 11h - 18h&lt;br /&gt;" displayable="1" sequence="99" />
<stlocattr stlocattr_id="@stlocattr_id_pt_BR_2_stloc_id_25" stloc_id="@stloc_id_25" language_id="&pt_BR;" name="DesignerStudio" displayname="Designer studio" value="true" displayvalue="verdadeiro" displayable="1" sequence="1" />
<stlocattr stlocattr_id="@stlocattr_id_pt_BR_3_stloc_id_25" stloc_id="@stloc_id_25" language_id="&pt_BR;" name="CappuccinoBar" displayname="Bar Cappuccino" value="true" displayvalue="verdadeiro" displayable="1" sequence="2" />
<stlocattr stlocattr_id="@stlocattr_id_pt_BR_4_stloc_id_25" stloc_id="@stloc_id_25" language_id="&pt_BR;" name="BeautyCenter" displayname="Clínica de Estética" value="true" displayvalue="verdadeiro" displayable="1" sequence="3" />
<stlocattr stlocattr_id="@stlocattr_id_pt_BR_5_stloc_id_25" stloc_id="@stloc_id_25" language_id="&pt_BR;" name="Electronics" displayname="Eletrônicos" value="true" displayvalue="verdadeiro" displayable="1" sequence="4" />
<stlocattr stlocattr_id="@stlocattr_id_pt_BR_6_stloc_id_25" stloc_id="@stloc_id_25" language_id="&pt_BR;" name="SushiRestaurant" displayname="Restaurante de Sushi" value="true" displayvalue="verdadeiro" displayable="1" sequence="5" />
<stlocattr stlocattr_id="@stlocattr_id_pt_BR_7_stloc_id_25" stloc_id="@stloc_id_25" language_id="&pt_BR;" name="Type" displayname="Tipo" value="Regular Store" displayvalue="Loja Regular" displayable="1" sequence="6" />

<stlocattr stlocattr_id="@stlocattr_id_pt_BR_1_stloc_id_26" stloc_id="@stloc_id_26" language_id="&pt_BR;" name="StoreHours" displayname="Horários de Funcionamento" value="Mon-Fri: 10am - 9pm&lt;br /&gt;Sat: 9am - 7pm&lt;br /&gt;Sun: 11am - 6pm&lt;br /&gt;" displayvalue="Seg-Sex: 10h - 21h&lt;br /&gt;Sáb: 9h - 19h&lt;br /&gt;Dom: 11h - 18h&lt;br /&gt;" displayable="1" sequence="99" />
<stlocattr stlocattr_id="@stlocattr_id_pt_BR_2_stloc_id_26" stloc_id="@stloc_id_26" language_id="&pt_BR;" name="BeautyCenter" displayname="Clínica de Estética" value="true" displayvalue="verdadeiro" displayable="1" sequence="1" />
<stlocattr stlocattr_id="@stlocattr_id_pt_BR_3_stloc_id_26" stloc_id="@stloc_id_26" language_id="&pt_BR;" name="CappuccinoBar" displayname="Bar Cappuccino" value="true" displayvalue="verdadeiro" displayable="1" sequence="2" />
<stlocattr stlocattr_id="@stlocattr_id_pt_BR_4_stloc_id_26" stloc_id="@stloc_id_26" language_id="&pt_BR;" name="Type" displayname="Tipo" value="Outlet Store" displayvalue="Supermercado" displayable="1" sequence="3" />

<stlocattr stlocattr_id="@stlocattr_id_pt_BR_1_stloc_id_27" stloc_id="@stloc_id_27" language_id="&pt_BR;" name="StoreHours" displayname="Horários de Funcionamento" value="Mon-Fri: 10am - 9pm&lt;br /&gt;Sat: 9am - 7pm&lt;br /&gt;Sun: 11am - 6pm&lt;br /&gt;" displayvalue="Seg-Sex: 10h - 21h&lt;br /&gt;Sáb: 9h - 19h&lt;br /&gt;Dom: 11h - 18h&lt;br /&gt;" displayable="1" sequence="99" />
<stlocattr stlocattr_id="@stlocattr_id_pt_BR_2_stloc_id_27" stloc_id="@stloc_id_27" language_id="&pt_BR;" name="Electronics" displayname="Eletrônicos" value="true" displayvalue="verdadeiro" displayable="1" sequence="1" />
<stlocattr stlocattr_id="@stlocattr_id_pt_BR_3_stloc_id_27" stloc_id="@stloc_id_27" language_id="&pt_BR;" name="CappuccinoBar" displayname="Bar Cappuccino" value="true" displayvalue="verdadeiro" displayable="1" sequence="2" />
<stlocattr stlocattr_id="@stlocattr_id_pt_BR_4_stloc_id_27" stloc_id="@stloc_id_27" language_id="&pt_BR;" name="Type" displayname="Tipo" value="Outlet Store" displayvalue="Supermercado" displayable="1" sequence="3" />

<stlocattr stlocattr_id="@stlocattr_id_pt_BR_1_stloc_id_28" stloc_id="@stloc_id_28" language_id="&pt_BR;" name="StoreHours" displayname="Horários de Funcionamento" value="Mon-Fri: 10am - 9pm&lt;br /&gt;Sat: 9am - 7pm&lt;br /&gt;Sun: 11am - 6pm&lt;br /&gt;" displayvalue="Seg-Sex: 10h - 21h&lt;br /&gt;Sáb: 9h - 19h&lt;br /&gt;Dom: 11h - 18h&lt;br /&gt;" displayable="1" sequence="99" />
<stlocattr stlocattr_id="@stlocattr_id_pt_BR_2_stloc_id_28" stloc_id="@stloc_id_28" language_id="&pt_BR;" name="DesignerStudio" displayname="Designer studio" value="true" displayvalue="verdadeiro" displayable="1" sequence="1" />
<stlocattr stlocattr_id="@stlocattr_id_pt_BR_3_stloc_id_28" stloc_id="@stloc_id_28" language_id="&pt_BR;" name="CappuccinoBar" displayname="Bar Cappuccino" value="true" displayvalue="verdadeiro" displayable="1" sequence="2" />
<stlocattr stlocattr_id="@stlocattr_id_pt_BR_4_stloc_id_28" stloc_id="@stloc_id_28" language_id="&pt_BR;" name="BeautyCenter" displayname="Clínica de Estética" value="true" displayvalue="verdadeiro" displayable="1" sequence="3" />
<stlocattr stlocattr_id="@stlocattr_id_pt_BR_5_stloc_id_28" stloc_id="@stloc_id_28" language_id="&pt_BR;" name="Electronics" displayname="Eletrônicos" value="true" displayvalue="verdadeiro" displayable="1" sequence="4" />
<stlocattr stlocattr_id="@stlocattr_id_pt_BR_6_stloc_id_28" stloc_id="@stloc_id_28" language_id="&pt_BR;" name="SushiRestaurant" displayname="Restaurante de Sushi" value="true" displayvalue="verdadeiro" displayable="1" sequence="5" />
<stlocattr stlocattr_id="@stlocattr_id_pt_BR_7_stloc_id_28" stloc_id="@stloc_id_28" language_id="&pt_BR;" name="Type" displayname="Tipo" value="Express Store" displayvalue="Loja Expressa" displayable="1" sequence="6" />

<stlocattr stlocattr_id="@stlocattr_id_pt_BR_1_stloc_id_29" stloc_id="@stloc_id_29" language_id="&pt_BR;" name="StoreHours" displayname="Horários de Funcionamento" value="Mon-Fri: 10am - 9pm&lt;br /&gt;Sat: 9am - 7pm&lt;br /&gt;Sun: 11am - 6pm&lt;br /&gt;" displayvalue="Seg-Sex: 10h - 21h&lt;br /&gt;Sáb: 9h - 19h&lt;br /&gt;Dom: 11h - 18h&lt;br /&gt;" displayable="1" sequence="99" />
<stlocattr stlocattr_id="@stlocattr_id_pt_BR_2_stloc_id_29" stloc_id="@stloc_id_29" language_id="&pt_BR;" name="CappuccinoBar" displayname="Bar Cappuccino" value="true" displayvalue="verdadeiro" displayable="1" sequence="1" />
<stlocattr stlocattr_id="@stlocattr_id_pt_BR_3_stloc_id_29" stloc_id="@stloc_id_29" language_id="&pt_BR;" name="Type" displayname="Tipo" value="Outlet Store" displayvalue="Supermercado" displayable="1" sequence="2" />

<stlocattr stlocattr_id="@stlocattr_id_pt_BR_1_stloc_id_30" stloc_id="@stloc_id_30" language_id="&pt_BR;" name="StoreHours" displayname="Horários de Funcionamento" value="Mon-Fri: 10am - 9pm&lt;br /&gt;Sat: 9am - 7pm&lt;br /&gt;Sun: 11am - 6pm&lt;br /&gt;" displayvalue="Seg-Sex: 10h - 21h&lt;br /&gt;Sáb: 9h - 19h&lt;br /&gt;Dom: 11h - 18h&lt;br /&gt;" displayable="1" sequence="99" />
<stlocattr stlocattr_id="@stlocattr_id_pt_BR_2_stloc_id_30" stloc_id="@stloc_id_30" language_id="&pt_BR;" name="DesignerStudio" displayname="Designer studio" value="true" displayvalue="verdadeiro" displayable="1" sequence="1" />
<stlocattr stlocattr_id="@stlocattr_id_pt_BR_3_stloc_id_30" stloc_id="@stloc_id_30" language_id="&pt_BR;" name="Electronics" displayname="Eletrônicos" value="true" displayvalue="verdadeiro" displayable="1" sequence="2" />
<stlocattr stlocattr_id="@stlocattr_id_pt_BR_4_stloc_id_30" stloc_id="@stloc_id_30" language_id="&pt_BR;" name="SushiRestaurant" displayname="Restaurante de Sushi" value="true" displayvalue="verdadeiro" displayable="1" sequence="3" />
<stlocattr stlocattr_id="@stlocattr_id_pt_BR_5_stloc_id_30" stloc_id="@stloc_id_30" language_id="&pt_BR;" name="Type" displayname="Tipo" value="Regular Store" displayvalue="Loja Regular" displayable="1" sequence="4" />

<stlocattr stlocattr_id="@stlocattr_id_pt_BR_1_stloc_id_31" stloc_id="@stloc_id_31" language_id="&pt_BR;" name="StoreHours" displayname="Horários de Funcionamento" value="Mon-Fri: 10am - 9pm&lt;br /&gt;Sat: 9am - 7pm&lt;br /&gt;Sun: 11am - 6pm&lt;br /&gt;" displayvalue="Seg-Sex: 10h - 21h&lt;br /&gt;Sáb: 9h - 19h&lt;br /&gt;Dom: 11h - 18h&lt;br /&gt;" displayable="1" sequence="99" />
<stlocattr stlocattr_id="@stlocattr_id_pt_BR_2_stloc_id_31" stloc_id="@stloc_id_31" language_id="&pt_BR;" name="Electronics" displayname="Eletrônicos" value="true" displayvalue="verdadeiro" displayable="1" sequence="1" />
<stlocattr stlocattr_id="@stlocattr_id_pt_BR_3_stloc_id_31" stloc_id="@stloc_id_31" language_id="&pt_BR;" name="SushiRestaurant" displayname="Restaurante de Sushi" value="true" displayvalue="verdadeiro" displayable="1" sequence="2" />
<stlocattr stlocattr_id="@stlocattr_id_pt_BR_4_stloc_id_31" stloc_id="@stloc_id_31" language_id="&pt_BR;" name="Type" displayname="Tipo" value="Express Store" displayvalue="Loja Expressa" displayable="1" sequence="3" />

<stlocattr stlocattr_id="@stlocattr_id_pt_BR_1_stloc_id_32" stloc_id="@stloc_id_32" language_id="&pt_BR;" name="StoreHours" displayname="Horários de Funcionamento" value="Mon-Fri: 10am - 9pm&lt;br /&gt;Sat: 9am - 7pm&lt;br /&gt;Sun: 11am - 6pm&lt;br /&gt;" displayvalue="Seg-Sex: 10h - 21h&lt;br /&gt;Sáb: 9h - 19h&lt;br /&gt;Dom: 11h - 18h&lt;br /&gt;" displayable="1" sequence="99" />
<stlocattr stlocattr_id="@stlocattr_id_pt_BR_2_stloc_id_32" stloc_id="@stloc_id_32" language_id="&pt_BR;" name="DesignerStudio" displayname="Designer studio" value="true" displayvalue="verdadeiro" displayable="1" sequence="1" />
<stlocattr stlocattr_id="@stlocattr_id_pt_BR_3_stloc_id_32" stloc_id="@stloc_id_32" language_id="&pt_BR;" name="CappuccinoBar" displayname="Bar Cappuccino" value="true" displayvalue="verdadeiro" displayable="1" sequence="2" />
<stlocattr stlocattr_id="@stlocattr_id_pt_BR_4_stloc_id_32" stloc_id="@stloc_id_32" language_id="&pt_BR;" name="BeautyCenter" displayname="Clínica de Estética" value="true" displayvalue="verdadeiro" displayable="1" sequence="3" />
<stlocattr stlocattr_id="@stlocattr_id_pt_BR_5_stloc_id_32" stloc_id="@stloc_id_32" language_id="&pt_BR;" name="Electronics" displayname="Eletrônicos" value="true" displayvalue="verdadeiro" displayable="1" sequence="4" />
<stlocattr stlocattr_id="@stlocattr_id_pt_BR_6_stloc_id_32" stloc_id="@stloc_id_32" language_id="&pt_BR;" name="SushiRestaurant" displayname="Restaurante de Sushi" value="true" displayvalue="verdadeiro" displayable="1" sequence="5" />
<stlocattr stlocattr_id="@stlocattr_id_pt_BR_7_stloc_id_32" stloc_id="@stloc_id_32" language_id="&pt_BR;" name="Type" displayname="Tipo" value="Outlet Store" displayvalue="Supermercado" displayable="1" sequence="6" />

<stlocattr stlocattr_id="@stlocattr_id_pt_BR_1_stloc_id_33" stloc_id="@stloc_id_33" language_id="&pt_BR;" name="StoreHours" displayname="Horários de Funcionamento" value="Mon-Fri: 10am - 9pm&lt;br /&gt;Sat: 9am - 7pm&lt;br /&gt;Sun: 11am - 6pm&lt;br /&gt;" displayvalue="Seg-Sex: 10h - 21h&lt;br /&gt;Sáb: 9h - 19h&lt;br /&gt;Dom: 11h - 18h&lt;br /&gt;" displayable="1" sequence="99" />
<stlocattr stlocattr_id="@stlocattr_id_pt_BR_2_stloc_id_33" stloc_id="@stloc_id_33" language_id="&pt_BR;" name="Electronics" displayname="Eletrônicos" value="true" displayvalue="verdadeiro" displayable="1" sequence="1" />
<stlocattr stlocattr_id="@stlocattr_id_pt_BR_3_stloc_id_33" stloc_id="@stloc_id_33" language_id="&pt_BR;" name="CappuccinoBar" displayname="Bar Cappuccino" value="true" displayvalue="verdadeiro" displayable="1" sequence="2" />
<stlocattr stlocattr_id="@stlocattr_id_pt_BR_4_stloc_id_33" stloc_id="@stloc_id_33" language_id="&pt_BR;" name="Type" displayname="Tipo" value="Regular Store" displayvalue="Loja Regular" displayable="1" sequence="3" />

<stlocattr stlocattr_id="@stlocattr_id_pt_BR_1_stloc_id_34" stloc_id="@stloc_id_34" language_id="&pt_BR;" name="StoreHours" displayname="Horários de Funcionamento" value="Mon-Fri: 10am - 9pm&lt;br /&gt;Sat: 9am - 7pm&lt;br /&gt;Sun: 11am - 6pm&lt;br /&gt;" displayvalue="Seg-Sex: 10h - 21h&lt;br /&gt;Sáb: 9h - 19h&lt;br /&gt;Dom: 11h - 18h&lt;br /&gt;" displayable="1" sequence="99" />
<stlocattr stlocattr_id="@stlocattr_id_pt_BR_2_stloc_id_34" stloc_id="@stloc_id_34" language_id="&pt_BR;" name="DesignerStudio" displayname="Designer studio" value="true" displayvalue="verdadeiro" displayable="1" sequence="1" />
<stlocattr stlocattr_id="@stlocattr_id_pt_BR_3_stloc_id_34" stloc_id="@stloc_id_34" language_id="&pt_BR;" name="SushiRestaurant" displayname="Restaurante de Sushi" value="true" displayvalue="verdadeiro" displayable="1" sequence="2" />
<stlocattr stlocattr_id="@stlocattr_id_pt_BR_4_stloc_id_34" stloc_id="@stloc_id_34" language_id="&pt_BR;" name="Type" displayname="Tipo" value="Express Store" displayvalue="Loja Expressa" displayable="1" sequence="3" />

<stlocattr stlocattr_id="@stlocattr_id_pt_BR_1_stloc_id_35" stloc_id="@stloc_id_35" language_id="&pt_BR;" name="StoreHours" displayname="Horários de Funcionamento" value="Mon-Fri: 10am - 9pm&lt;br /&gt;Sat: 9am - 7pm&lt;br /&gt;Sun: 11am - 6pm&lt;br /&gt;" displayvalue="Seg-Sex: 10h - 21h&lt;br /&gt;Sáb: 9h - 19h&lt;br /&gt;Dom: 11h - 18h&lt;br /&gt;" displayable="1" sequence="99" />
<stlocattr stlocattr_id="@stlocattr_id_pt_BR_2_stloc_id_35" stloc_id="@stloc_id_35" language_id="&pt_BR;" name="SushiRestaurant" displayname="Restaurante de Sushi" value="true" displayvalue="verdadeiro" displayable="1" sequence="1" />
<stlocattr stlocattr_id="@stlocattr_id_pt_BR_3_stloc_id_35" stloc_id="@stloc_id_35" language_id="&pt_BR;" name="Type" displayname="Tipo" value="Outlet Store" displayvalue="Supermercado" displayable="1" sequence="2" />

<stlocattr stlocattr_id="@stlocattr_id_pt_BR_1_stloc_id_36" stloc_id="@stloc_id_36" language_id="&pt_BR;" name="StoreHours" displayname="Horários de Funcionamento" value="Mon-Fri: 10am - 9pm&lt;br /&gt;Sat: 9am - 7pm&lt;br /&gt;Sun: 11am - 6pm&lt;br /&gt;" displayvalue="Seg-Sex: 10h - 21h&lt;br /&gt;Sáb: 9h - 19h&lt;br /&gt;Dom: 11h - 18h&lt;br /&gt;" displayable="1" sequence="99" />
<stlocattr stlocattr_id="@stlocattr_id_pt_BR_2_stloc_id_36" stloc_id="@stloc_id_36" language_id="&pt_BR;" name="BeautyCenter" displayname="Clínica de Estética" value="true" displayvalue="verdadeiro" displayable="1" sequence="1" />
<stlocattr stlocattr_id="@stlocattr_id_pt_BR_3_stloc_id_36" stloc_id="@stloc_id_36" language_id="&pt_BR;" name="CappuccinoBar" displayname="Bar Cappuccino" value="true" displayvalue="verdadeiro" displayable="1" sequence="2" />
<stlocattr stlocattr_id="@stlocattr_id_pt_BR_4_stloc_id_36" stloc_id="@stloc_id_36" language_id="&pt_BR;" name="SushiRestaurant" displayname="Restaurante de Sushi" value="true" displayvalue="verdadeiro" displayable="1" sequence="3" />
<stlocattr stlocattr_id="@stlocattr_id_pt_BR_5_stloc_id_36" stloc_id="@stloc_id_36" language_id="&pt_BR;" name="Type" displayname="Tipo" value="Regular Store" displayvalue="Loja Regular" displayable="1" sequence="4" />

<stlocattr stlocattr_id="@stlocattr_id_pt_BR_1_stloc_id_37" stloc_id="@stloc_id_37" language_id="&pt_BR;" name="StoreHours" displayname="Horários de Funcionamento" value="Mon-Fri: 10am - 9pm&lt;br /&gt;Sat: 9am - 7pm&lt;br /&gt;Sun: 11am - 6pm&lt;br /&gt;" displayvalue="Seg-Sex: 10h - 21h&lt;br /&gt;Sáb: 9h - 19h&lt;br /&gt;Dom: 11h - 18h&lt;br /&gt;" displayable="1" sequence="99" />
<stlocattr stlocattr_id="@stlocattr_id_pt_BR_2_stloc_id_37" stloc_id="@stloc_id_37" language_id="&pt_BR;" name="BeautyCenter" displayname="Clínica de Estética" value="true" displayvalue="verdadeiro" displayable="1" sequence="1" />
<stlocattr stlocattr_id="@stlocattr_id_pt_BR_3_stloc_id_37" stloc_id="@stloc_id_37" language_id="&pt_BR;" name="CappuccinoBar" displayname="Bar Cappuccino" value="true" displayvalue="verdadeiro" displayable="1" sequence="2" />
<stlocattr stlocattr_id="@stlocattr_id_pt_BR_4_stloc_id_37" stloc_id="@stloc_id_37" language_id="&pt_BR;" name="DesignerStudio" displayname="Designer studio" value="true" displayvalue="verdadeiro" displayable="1" sequence="3" />
<stlocattr stlocattr_id="@stlocattr_id_pt_BR_5_stloc_id_37" stloc_id="@stloc_id_37" language_id="&pt_BR;" name="Type" displayname="Tipo" value="Express Store" displayvalue="Loja Expressa" displayable="1" sequence="4" />

<stlocattr stlocattr_id="@stlocattr_id_pt_BR_1_stloc_id_38" stloc_id="@stloc_id_38" language_id="&pt_BR;" name="StoreHours" displayname="Horários de Funcionamento" value="Mon-Fri: 10am - 9pm&lt;br /&gt;Sat: 9am - 7pm&lt;br /&gt;Sun: 11am - 6pm&lt;br /&gt;" displayvalue="Seg-Sex: 10h - 21h&lt;br /&gt;Sáb: 9h - 19h&lt;br /&gt;Dom: 11h - 18h&lt;br /&gt;" displayable="1" sequence="99" />
<stlocattr stlocattr_id="@stlocattr_id_pt_BR_2_stloc_id_38" stloc_id="@stloc_id_38" language_id="&pt_BR;" name="DesignerStudio" displayname="Designer studio" value="true" displayvalue="verdadeiro" displayable="1" sequence="1" />
<stlocattr stlocattr_id="@stlocattr_id_pt_BR_3_stloc_id_38" stloc_id="@stloc_id_38" language_id="&pt_BR;" name="Electronics" displayname="Eletrônicos" value="true" displayvalue="verdadeiro" displayable="1" sequence="2" />
<stlocattr stlocattr_id="@stlocattr_id_pt_BR_4_stloc_id_38" stloc_id="@stloc_id_38" language_id="&pt_BR;" name="BeautyCenter" displayname="Clínica de Estética" value="true" displayvalue="verdadeiro" displayable="1" sequence="3" />
<stlocattr stlocattr_id="@stlocattr_id_pt_BR_5_stloc_id_38" stloc_id="@stloc_id_38" language_id="&pt_BR;" name="Type" displayname="Tipo" value="Outlet Store" displayvalue="Supermercado" displayable="1" sequence="4" />

<stlocattr stlocattr_id="@stlocattr_id_pt_BR_1_stloc_id_39" stloc_id="@stloc_id_39" language_id="&pt_BR;" name="StoreHours" displayname="Horários de Funcionamento" value="Mon-Fri: 10am - 9pm&lt;br /&gt;Sat: 9am - 7pm&lt;br /&gt;Sun: 11am - 6pm&lt;br /&gt;" displayvalue="Seg-Sex: 10h - 21h&lt;br /&gt;Sáb: 9h - 19h&lt;br /&gt;Dom: 11h - 18h&lt;br /&gt;" displayable="1" sequence="99" />
<stlocattr stlocattr_id="@stlocattr_id_pt_BR_2_stloc_id_39" stloc_id="@stloc_id_39" language_id="&pt_BR;" name="BeautyCenter" displayname="Clínica de Estética" value="true" displayvalue="verdadeiro" displayable="1" sequence="1" />
<stlocattr stlocattr_id="@stlocattr_id_pt_BR_3_stloc_id_39" stloc_id="@stloc_id_39" language_id="&pt_BR;" name="CappuccinoBar" displayname="Bar Cappuccino" value="true" displayvalue="verdadeiro" displayable="1" sequence="2" />
<stlocattr stlocattr_id="@stlocattr_id_pt_BR_4_stloc_id_39" stloc_id="@stloc_id_39" language_id="&pt_BR;" name="SushiRestaurant" displayname="Restaurante de Sushi" value="true" displayvalue="verdadeiro" displayable="1" sequence="3" />
<stlocattr stlocattr_id="@stlocattr_id_pt_BR_5_stloc_id_39" stloc_id="@stloc_id_39" language_id="&pt_BR;" name="Type" displayname="Tipo" value="Regular Store" displayvalue="Loja Regular" displayable="1" sequence="4" />

<stlocattr stlocattr_id="@stlocattr_id_pt_BR_1_stloc_id_40" stloc_id="@stloc_id_40" language_id="&pt_BR;" name="StoreHours" displayname="Horários de Funcionamento" value="Mon-Fri: 10am - 9pm&lt;br /&gt;Sat: 9am - 7pm&lt;br /&gt;Sun: 11am - 6pm&lt;br /&gt;" displayvalue="Seg-Sex: 10h - 21h&lt;br /&gt;Sáb: 9h - 19h&lt;br /&gt;Dom: 11h - 18h&lt;br /&gt;" displayable="1" sequence="99" />
<stlocattr stlocattr_id="@stlocattr_id_pt_BR_2_stloc_id_40" stloc_id="@stloc_id_40" language_id="&pt_BR;" name="CappuccinoBar" displayname="Bar Cappuccino" value="true" displayvalue="verdadeiro" displayable="1" sequence="1" />
<stlocattr stlocattr_id="@stlocattr_id_pt_BR_3_stloc_id_40" stloc_id="@stloc_id_40" language_id="&pt_BR;" name="SushiRestaurant" displayname="Restaurante de Sushi" value="true" displayvalue="verdadeiro" displayable="1" sequence="2" />
<stlocattr stlocattr_id="@stlocattr_id_pt_BR_4_stloc_id_40" stloc_id="@stloc_id_40" language_id="&pt_BR;" name="Type" displayname="Tipo" value="Outlet Store" displayvalue="Supermercado" displayable="1" sequence="3" />

<stlocattr stlocattr_id="@stlocattr_id_pt_BR_1_stloc_id_41" stloc_id="@stloc_id_41" language_id="&pt_BR;" name="StoreHours" displayname="Horários de Funcionamento" value="Mon-Fri: 10am - 9pm&lt;br /&gt;Sat: 9am - 7pm&lt;br /&gt;Sun: 11am - 6pm&lt;br /&gt;" displayvalue="Seg-Sex: 10h - 21h&lt;br /&gt;Sáb: 9h - 19h&lt;br /&gt;Dom: 11h - 18h&lt;br /&gt;" displayable="1" sequence="99" />
<stlocattr stlocattr_id="@stlocattr_id_pt_BR_2_stloc_id_41" stloc_id="@stloc_id_41" language_id="&pt_BR;" name="Electronics" displayname="Eletrônicos" value="true" displayvalue="verdadeiro" displayable="1" sequence="1" />
<stlocattr stlocattr_id="@stlocattr_id_pt_BR_3_stloc_id_41" stloc_id="@stloc_id_41" language_id="&pt_BR;" name="Type" displayname="Tipo" value="Express Store" displayvalue="Loja Expressa" displayable="1" sequence="2" />

<stlocattr stlocattr_id="@stlocattr_id_pt_BR_1_stloc_id_42" stloc_id="@stloc_id_42" language_id="&pt_BR;" name="StoreHours" displayname="Horários de Funcionamento" value="Mon-Fri: 10am - 9pm&lt;br /&gt;Sat: 9am - 7pm&lt;br /&gt;Sun: 11am - 6pm&lt;br /&gt;" displayvalue="Seg-Sex: 10h - 21h&lt;br /&gt;Sáb: 9h - 19h&lt;br /&gt;Dom: 11h - 18h&lt;br /&gt;" displayable="1" sequence="99" />
<stlocattr stlocattr_id="@stlocattr_id_pt_BR_2_stloc_id_42" stloc_id="@stloc_id_42" language_id="&pt_BR;" name="DesignerStudio" displayname="Designer studio" value="true" displayvalue="verdadeiro" displayable="1" sequence="1" />
<stlocattr stlocattr_id="@stlocattr_id_pt_BR_3_stloc_id_42" stloc_id="@stloc_id_42" language_id="&pt_BR;" name="CappuccinoBar" displayname="Bar Cappuccino" value="true" displayvalue="verdadeiro" displayable="1" sequence="2" />
<stlocattr stlocattr_id="@stlocattr_id_pt_BR_4_stloc_id_42" stloc_id="@stloc_id_42" language_id="&pt_BR;" name="BeautyCenter" displayname="Clínica de Estética" value="true" displayvalue="verdadeiro" displayable="1" sequence="3" />
<stlocattr stlocattr_id="@stlocattr_id_pt_BR_5_stloc_id_42" stloc_id="@stloc_id_42" language_id="&pt_BR;" name="SushiRestaurant" displayname="Restaurante de Sushi" value="true" displayvalue="verdadeiro" displayable="1" sequence="4" />
<stlocattr stlocattr_id="@stlocattr_id_pt_BR_6_stloc_id_42" stloc_id="@stloc_id_42" language_id="&pt_BR;" name="Type" displayname="Tipo" value="Regular Store" displayvalue="Loja Regular" displayable="1" sequence="5" />

<stlocattr stlocattr_id="@stlocattr_id_pt_BR_1_stloc_id_43" stloc_id="@stloc_id_43" language_id="&pt_BR;" name="StoreHours" displayname="Horários de Funcionamento" value="Mon-Fri: 10am - 9pm&lt;br /&gt;Sat: 9am - 7pm&lt;br /&gt;Sun: 11am - 6pm&lt;br /&gt;" displayvalue="Seg-Sex: 10h - 21h&lt;br /&gt;Sáb: 9h - 19h&lt;br /&gt;Dom: 11h - 18h&lt;br /&gt;" displayable="1" sequence="99" />
<stlocattr stlocattr_id="@stlocattr_id_pt_BR_2_stloc_id_43" stloc_id="@stloc_id_43" language_id="&pt_BR;" name="BeautyCenter" displayname="Clínica de Estética" value="true" displayvalue="verdadeiro" displayable="1" sequence="1" />
<stlocattr stlocattr_id="@stlocattr_id_pt_BR_3_stloc_id_43" stloc_id="@stloc_id_43" language_id="&pt_BR;" name="Electronics" displayname="Eletrônicos" value="true" displayvalue="verdadeiro" displayable="1" sequence="2" />
<stlocattr stlocattr_id="@stlocattr_id_pt_BR_4_stloc_id_43" stloc_id="@stloc_id_43" language_id="&pt_BR;" name="Type" displayname="Tipo" value="Outlet Store" displayvalue="Supermercado" displayable="1" sequence="3" />

<stlocattr stlocattr_id="@stlocattr_id_pt_BR_1_stloc_id_44" stloc_id="@stloc_id_44" language_id="&pt_BR;" name="StoreHours" displayname="Horários de Funcionamento" value="Mon-Fri: 10am - 9pm&lt;br /&gt;Sat: 9am - 7pm&lt;br /&gt;Sun: 11am - 6pm&lt;br /&gt;" displayvalue="Seg-Sex: 10h - 21h&lt;br /&gt;Sáb: 9h - 19h&lt;br /&gt;Dom: 11h - 18h&lt;br /&gt;" displayable="1" sequence="99" />
<stlocattr stlocattr_id="@stlocattr_id_pt_BR_2_stloc_id_44" stloc_id="@stloc_id_44" language_id="&pt_BR;" name="BeautyCenter" displayname="Clínica de Estética" value="true" displayvalue="verdadeiro" displayable="1" sequence="1" />
<stlocattr stlocattr_id="@stlocattr_id_pt_BR_3_stloc_id_44" stloc_id="@stloc_id_44" language_id="&pt_BR;" name="SushiRestaurant" displayname="Restaurante de Sushi" value="true" displayvalue="verdadeiro" displayable="1" sequence="2" />
<stlocattr stlocattr_id="@stlocattr_id_pt_BR_4_stloc_id_44" stloc_id="@stloc_id_44" language_id="&pt_BR;" name="Type" displayname="Tipo" value="Express Store" displayvalue="Loja Expressa" displayable="1" sequence="3" />

<stlocattr stlocattr_id="@stlocattr_id_pt_BR_1_stloc_id_45" stloc_id="@stloc_id_45" language_id="&pt_BR;" name="StoreHours" displayname="Horários de Funcionamento" value="Mon-Fri: 10am - 9pm&lt;br /&gt;Sat: 9am - 7pm&lt;br /&gt;Sun: 11am - 6pm&lt;br /&gt;" displayvalue="Seg-Sex: 10h - 21h&lt;br /&gt;Sáb: 9h - 19h&lt;br /&gt;Dom: 11h - 18h&lt;br /&gt;" displayable="1" sequence="99" />
<stlocattr stlocattr_id="@stlocattr_id_pt_BR_2_stloc_id_45" stloc_id="@stloc_id_45" language_id="&pt_BR;" name="DesignerStudio" displayname="Designer studio" value="true" displayvalue="verdadeiro" displayable="1" sequence="1" />
<stlocattr stlocattr_id="@stlocattr_id_pt_BR_3_stloc_id_45" stloc_id="@stloc_id_45" language_id="&pt_BR;" name="Electronics" displayname="Eletrônicos" value="true" displayvalue="verdadeiro" displayable="1" sequence="2" />
<stlocattr stlocattr_id="@stlocattr_id_pt_BR_4_stloc_id_45" stloc_id="@stloc_id_45" language_id="&pt_BR;" name="Type" displayname="Tipo" value="Outlet Store" displayvalue="Supermercado" displayable="1" sequence="3" />

<stlocattr stlocattr_id="@stlocattr_id_pt_BR_1_stloc_id_46" stloc_id="@stloc_id_46" language_id="&pt_BR;" name="StoreHours" displayname="Horários de Funcionamento" value="Mon-Fri: 10am - 9pm&lt;br /&gt;Sat: 9am - 7pm&lt;br /&gt;Sun: 11am - 6pm&lt;br /&gt;" displayvalue="Seg-Sex: 10h - 21h&lt;br /&gt;Sáb: 9h - 19h&lt;br /&gt;Dom: 11h - 18h&lt;br /&gt;" displayable="1" sequence="99" />
<stlocattr stlocattr_id="@stlocattr_id_pt_BR_2_stloc_id_46" stloc_id="@stloc_id_46" language_id="&pt_BR;" name="CappuccinoBar" displayname="Bar Cappuccino" value="true" displayvalue="verdadeiro" displayable="1" sequence="1" />
<stlocattr stlocattr_id="@stlocattr_id_pt_BR_3_stloc_id_46" stloc_id="@stloc_id_46" language_id="&pt_BR;" name="SushiRestaurant" displayname="Restaurante de Sushi" value="true" displayvalue="verdadeiro" displayable="1" sequence="2" />
<stlocattr stlocattr_id="@stlocattr_id_pt_BR_4_stloc_id_46" stloc_id="@stloc_id_46" language_id="&pt_BR;" name="Type" displayname="Tipo" value="Express Store" displayvalue="Loja Expressa" displayable="1" sequence="3" />

<stlocattr stlocattr_id="@stlocattr_id_pt_BR_1_stloc_id_47" stloc_id="@stloc_id_47" language_id="&pt_BR;" name="StoreHours" displayname="Horários de Funcionamento" value="Mon-Fri: 10am - 9pm&lt;br /&gt;Sat: 9am - 7pm&lt;br /&gt;Sun: 11am - 6pm&lt;br /&gt;" displayvalue="Seg-Sex: 10h - 21h&lt;br /&gt;Sáb: 9h - 19h&lt;br /&gt;Dom: 11h - 18h&lt;br /&gt;" displayable="1" sequence="99" />
<stlocattr stlocattr_id="@stlocattr_id_pt_BR_2_stloc_id_47" stloc_id="@stloc_id_47" language_id="&pt_BR;" name="DesignerStudio" displayname="Designer studio" value="true" displayvalue="verdadeiro" displayable="1" sequence="1" />
<stlocattr stlocattr_id="@stlocattr_id_pt_BR_3_stloc_id_47" stloc_id="@stloc_id_47" language_id="&pt_BR;" name="BeautyCenter" displayname="Clínica de Estética" value="true" displayvalue="verdadeiro" displayable="1" sequence="2" />
<stlocattr stlocattr_id="@stlocattr_id_pt_BR_4_stloc_id_47" stloc_id="@stloc_id_47" language_id="&pt_BR;" name="Type" displayname="Tipo" value="Regular Store" displayvalue="Loja Regular" displayable="1" sequence="3" />

<stlocattr stlocattr_id="@stlocattr_id_pt_BR_1_stloc_id_48" stloc_id="@stloc_id_48" language_id="&pt_BR;" name="StoreHours" displayname="Horários de Funcionamento" value="Mon-Fri: 10am - 9pm&lt;br /&gt;Sat: 9am - 7pm&lt;br /&gt;Sun: 11am - 6pm&lt;br /&gt;" displayvalue="Seg-Sex: 10h - 21h&lt;br /&gt;Sáb: 9h - 19h&lt;br /&gt;Dom: 11h - 18h&lt;br /&gt;" displayable="1" sequence="99" />
<stlocattr stlocattr_id="@stlocattr_id_pt_BR_2_stloc_id_48" stloc_id="@stloc_id_48" language_id="&pt_BR;" name="DesignerStudio" displayname="Designer studio" value="true" displayvalue="verdadeiro" displayable="1" sequence="1" />
<stlocattr stlocattr_id="@stlocattr_id_pt_BR_3_stloc_id_48" stloc_id="@stloc_id_48" language_id="&pt_BR;" name="Electronics" displayname="Eletrônicos" value="true" displayvalue="verdadeiro" displayable="1" sequence="2" />
<stlocattr stlocattr_id="@stlocattr_id_pt_BR_4_stloc_id_48" stloc_id="@stloc_id_48" language_id="&pt_BR;" name="BeautyCenter" displayname="Clínica de Estética" value="true" displayvalue="verdadeiro" displayable="1" sequence="3" />
<stlocattr stlocattr_id="@stlocattr_id_pt_BR_5_stloc_id_48" stloc_id="@stloc_id_48" language_id="&pt_BR;" name="SushiRestaurant" displayname="Restaurante de Sushi" value="true" displayvalue="verdadeiro" displayable="1" sequence="4" />
<stlocattr stlocattr_id="@stlocattr_id_pt_BR_6_stloc_id_48" stloc_id="@stloc_id_48" language_id="&pt_BR;" name="Type" displayname="Tipo" value="Regular Store" displayvalue="Loja Regular" displayable="1" sequence="5" />

<stlocattr stlocattr_id="@stlocattr_id_pt_BR_1_stloc_id_49" stloc_id="@stloc_id_49" language_id="&pt_BR;" name="StoreHours" displayname="Horários de Funcionamento" value="Mon-Fri: 10am - 9pm&lt;br /&gt;Sat: 9am - 7pm&lt;br /&gt;Sun: 11am - 6pm&lt;br /&gt;" displayvalue="Seg-Sex: 10h - 21h&lt;br /&gt;Sáb: 9h - 19h&lt;br /&gt;Dom: 11h - 18h&lt;br /&gt;" displayable="1" sequence="99" />
<stlocattr stlocattr_id="@stlocattr_id_pt_BR_2_stloc_id_49" stloc_id="@stloc_id_49" language_id="&pt_BR;" name="DesignerStudio" displayname="Designer studio" value="true" displayvalue="verdadeiro" displayable="1" sequence="1" />
<stlocattr stlocattr_id="@stlocattr_id_pt_BR_3_stloc_id_49" stloc_id="@stloc_id_49" language_id="&pt_BR;" name="CappuccinoBar" displayname="Bar Cappuccino" value="true" displayvalue="verdadeiro" displayable="1" sequence="2" />
<stlocattr stlocattr_id="@stlocattr_id_pt_BR_4_stloc_id_49" stloc_id="@stloc_id_49" language_id="&pt_BR;" name="BeautyCenter" displayname="Clínica de Estética" value="true" displayvalue="verdadeiro" displayable="1" sequence="3" />
<stlocattr stlocattr_id="@stlocattr_id_pt_BR_5_stloc_id_49" stloc_id="@stloc_id_49" language_id="&pt_BR;" name="Electronics" displayname="Eletrônicos" value="true" displayvalue="verdadeiro" displayable="1" sequence="4" />
<stlocattr stlocattr_id="@stlocattr_id_pt_BR_6_stloc_id_49" stloc_id="@stloc_id_49" language_id="&pt_BR;" name="SushiRestaurant" displayname="Restaurante de Sushi" value="true" displayvalue="verdadeiro" displayable="1" sequence="5" />
<stlocattr stlocattr_id="@stlocattr_id_pt_BR_7_stloc_id_49" stloc_id="@stloc_id_49" language_id="&pt_BR;" name="Type" displayname="Tipo" value="Regular Store" displayvalue="Loja Regular" displayable="1" sequence="6" />

<stlocattr stlocattr_id="@stlocattr_id_pt_BR_1_stloc_id_50" stloc_id="@stloc_id_50" language_id="&pt_BR;" name="StoreHours" displayname="Horários de Funcionamento" value="Mon-Fri: 10am - 9pm&lt;br /&gt;Sat: 9am - 7pm&lt;br /&gt;Sun: 11am - 6pm&lt;br /&gt;" displayvalue="Seg-Sex: 10h - 21h&lt;br /&gt;Sáb: 9h - 19h&lt;br /&gt;Dom: 11h - 18h&lt;br /&gt;" displayable="1" sequence="99" />
<stlocattr stlocattr_id="@stlocattr_id_pt_BR_2_stloc_id_50" stloc_id="@stloc_id_50" language_id="&pt_BR;" name="CappuccinoBar" displayname="Bar Cappuccino" value="true" displayvalue="verdadeiro" displayable="1" sequence="1" />
<stlocattr stlocattr_id="@stlocattr_id_pt_BR_3_stloc_id_50" stloc_id="@stloc_id_50" language_id="&pt_BR;" name="SushiRestaurant" displayname="Restaurante de Sushi" value="true" displayvalue="verdadeiro" displayable="1" sequence="2" />
<stlocattr stlocattr_id="@stlocattr_id_pt_BR_4_stloc_id_50" stloc_id="@stloc_id_50" language_id="&pt_BR;" name="Type" displayname="Tipo" value="Express Store" displayvalue="Loja Expressa" displayable="1" sequence="3" />

<stlocattr stlocattr_id="@stlocattr_id_pt_BR_1_stloc_id_51" stloc_id="@stloc_id_51" language_id="&pt_BR;" name="StoreHours" displayname="Horários de Funcionamento" value="Mon-Fri: 10am - 9pm&lt;br /&gt;Sat: 9am - 7pm&lt;br /&gt;Sun: 11am - 6pm&lt;br /&gt;" displayvalue="Seg-Sex: 10h - 21h&lt;br /&gt;Sáb: 9h - 19h&lt;br /&gt;Dom: 11h - 18h&lt;br /&gt;" displayable="1" sequence="99" />
<stlocattr stlocattr_id="@stlocattr_id_pt_BR_2_stloc_id_51" stloc_id="@stloc_id_51" language_id="&pt_BR;" name="DesignerStudio" displayname="Designer studio" value="true" displayvalue="verdadeiro" displayable="1" sequence="1" />
<stlocattr stlocattr_id="@stlocattr_id_pt_BR_3_stloc_id_51" stloc_id="@stloc_id_51" language_id="&pt_BR;" name="Electronics" displayname="Eletrônicos" value="true" displayvalue="verdadeiro" displayable="1" sequence="2" />
<stlocattr stlocattr_id="@stlocattr_id_pt_BR_4_stloc_id_51" stloc_id="@stloc_id_51" language_id="&pt_BR;" name="BeautyCenter" displayname="Clínica de Estética" value="true" displayvalue="verdadeiro" displayable="1" sequence="3" />
<stlocattr stlocattr_id="@stlocattr_id_pt_BR_5_stloc_id_51" stloc_id="@stloc_id_51" language_id="&pt_BR;" name="Type" displayname="Tipo" value="Outlet Store" displayvalue="Supermercado" displayable="1" sequence="4" />

<stlocattr stlocattr_id="@stlocattr_id_pt_BR_1_stloc_id_52" stloc_id="@stloc_id_52" language_id="&pt_BR;" name="StoreHours" displayname="Horários de Funcionamento" value="Mon-Fri: 10am - 9pm&lt;br /&gt;Sat: 9am - 7pm&lt;br /&gt;Sun: 11am - 6pm&lt;br /&gt;" displayvalue="Seg-Sex: 10h - 21h&lt;br /&gt;Sáb: 9h - 19h&lt;br /&gt;Dom: 11h - 18h&lt;br /&gt;" displayable="1" sequence="99" />
<stlocattr stlocattr_id="@stlocattr_id_pt_BR_2_stloc_id_52" stloc_id="@stloc_id_52" language_id="&pt_BR;" name="DesignerStudio" displayname="Designer studio" value="true" displayvalue="verdadeiro" displayable="1" sequence="1" />
<stlocattr stlocattr_id="@stlocattr_id_pt_BR_3_stloc_id_52" stloc_id="@stloc_id_52" language_id="&pt_BR;" name="Electronics" displayname="Eletrônicos" value="true" displayvalue="verdadeiro" displayable="1" sequence="2" />
<stlocattr stlocattr_id="@stlocattr_id_pt_BR_4_stloc_id_52" stloc_id="@stloc_id_52" language_id="&pt_BR;" name="Type" displayname="Tipo" value="Outlet Store" displayvalue="Supermercado" displayable="1" sequence="3" />

<stlocattr stlocattr_id="@stlocattr_id_pt_BR_1_stloc_id_53" stloc_id="@stloc_id_53" language_id="&pt_BR;" name="StoreHours" displayname="Horários de Funcionamento" value="Mon-Fri: 10am - 9pm&lt;br /&gt;Sat: 9am - 7pm&lt;br /&gt;Sun: 11am - 6pm&lt;br /&gt;" displayvalue="Seg-Sex: 10h - 21h&lt;br /&gt;Sáb: 9h - 19h&lt;br /&gt;Dom: 11h - 18h&lt;br /&gt;" displayable="1" sequence="99" />
<stlocattr stlocattr_id="@stlocattr_id_pt_BR_2_stloc_id_53" stloc_id="@stloc_id_53" language_id="&pt_BR;" name="DesignerStudio" displayname="Designer studio" value="true" displayvalue="verdadeiro" displayable="1" sequence="1" />
<stlocattr stlocattr_id="@stlocattr_id_pt_BR_3_stloc_id_53" stloc_id="@stloc_id_53" language_id="&pt_BR;" name="CappuccinoBar" displayname="Bar Cappuccino" value="true" displayvalue="verdadeiro" displayable="1" sequence="2" />
<stlocattr stlocattr_id="@stlocattr_id_pt_BR_4_stloc_id_53" stloc_id="@stloc_id_53" language_id="&pt_BR;" name="BeautyCenter" displayname="Clínica de Estética" value="true" displayvalue="verdadeiro" displayable="1" sequence="3" />
<stlocattr stlocattr_id="@stlocattr_id_pt_BR_5_stloc_id_53" stloc_id="@stloc_id_53" language_id="&pt_BR;" name="Electronics" displayname="Eletrônicos" value="true" displayvalue="verdadeiro" displayable="1" sequence="4" />
<stlocattr stlocattr_id="@stlocattr_id_pt_BR_6_stloc_id_53" stloc_id="@stloc_id_53" language_id="&pt_BR;" name="SushiRestaurant" displayname="Restaurante de Sushi" value="true" displayvalue="verdadeiro" displayable="1" sequence="5" />
<stlocattr stlocattr_id="@stlocattr_id_pt_BR_7_stloc_id_53" stloc_id="@stloc_id_53" language_id="&pt_BR;" name="Type" displayname="Tipo" value="Regular Store" displayvalue="Loja Regular" displayable="1" sequence="6" />

<stlocattr stlocattr_id="@stlocattr_id_pt_BR_1_stloc_id_54" stloc_id="@stloc_id_54" language_id="&pt_BR;" name="StoreHours" displayname="Horários de Funcionamento" value="Mon-Fri: 10am - 9pm&lt;br /&gt;Sat: 9am - 7pm&lt;br /&gt;Sun: 11am - 6pm&lt;br /&gt;" displayvalue="Seg-Sex: 10h - 21h&lt;br /&gt;Sáb: 9h - 19h&lt;br /&gt;Dom: 11h - 18h&lt;br /&gt;" displayable="1" sequence="99" />
<stlocattr stlocattr_id="@stlocattr_id_pt_BR_2_stloc_id_54" stloc_id="@stloc_id_54" language_id="&pt_BR;" name="CappuccinoBar" displayname="Bar Cappuccino" value="true" displayvalue="verdadeiro" displayable="1" sequence="1" />
<stlocattr stlocattr_id="@stlocattr_id_pt_BR_3_stloc_id_54" stloc_id="@stloc_id_54" language_id="&pt_BR;" name="SushiRestaurant" displayname="Restaurante de Sushi" value="true" displayvalue="verdadeiro" displayable="1" sequence="2" />
<stlocattr stlocattr_id="@stlocattr_id_pt_BR_4_stloc_id_54" stloc_id="@stloc_id_54" language_id="&pt_BR;" name="Type" displayname="Tipo" value="Express Store" displayvalue="Loja Expressa" displayable="1" sequence="3" />

<stlocattr stlocattr_id="@stlocattr_id_pt_BR_1_stloc_id_55" stloc_id="@stloc_id_55" language_id="&pt_BR;" name="StoreHours" displayname="Horários de Funcionamento" value="Mon-Fri: 10am - 9pm&lt;br /&gt;Sat: 9am - 7pm&lt;br /&gt;Sun: 11am - 6pm&lt;br /&gt;" displayvalue="Seg-Sex: 10h - 21h&lt;br /&gt;Sáb: 9h - 19h&lt;br /&gt;Dom: 11h - 18h&lt;br /&gt;" displayable="1" sequence="99" />
<stlocattr stlocattr_id="@stlocattr_id_pt_BR_2_stloc_id_55" stloc_id="@stloc_id_55" language_id="&pt_BR;" name="DesignerStudio" displayname="Designer studio" value="true" displayvalue="verdadeiro" displayable="1" sequence="1" />
<stlocattr stlocattr_id="@stlocattr_id_pt_BR_3_stloc_id_55" stloc_id="@stloc_id_55" language_id="&pt_BR;" name="Electronics" displayname="Eletrônicos" value="true" displayvalue="verdadeiro" displayable="1" sequence="2" />
<stlocattr stlocattr_id="@stlocattr_id_pt_BR_4_stloc_id_55" stloc_id="@stloc_id_55" language_id="&pt_BR;" name="Type" displayname="Tipo" value="Outlet Store" displayvalue="Supermercado" displayable="1" sequence="3" />
